orbnet/.ruff_cache/.gitignore
orbnet/.ruff_cache/0.13.2/1754157866898536654
orbnet/.ruff_cache/CACHEDIR.TAG
orbnet/__init__.py
orbnet/client.py
orbnet/mcp_server.py
orbnet/models.py
orbnet-0.1.2.dist-info/WHEEL
orbnet-0.1.2.dist-info/entry_points.txt
orbnet-0.1.2.dist-info/METADATA
orbnet-0.1.2.dist-info/RECORD
