Metadata-Version: 2.3
Name: orbnet
Version: 0.1.2
Summary: Retrieve network quality data from Orb Sensor
Keywords: 
Author: Brian Connelly, Orb Forge Incorporated
Author-email: Brian Connelly <bdc@bconnelly.net>
License: MIT License
Classifier: Development Status :: 3 - Alpha
Classifier: License :: OSI Approved :: MIT License
Classifier: Programming Language :: Python
Classifier: Programming Language :: Python :: 3
Classifier: Programming Language :: Python :: 3.13
Classifier: Topic :: System :: Networking :: Monitoring
Requires-Dist: httpx>=0.28.1
Requires-Dist: pydantic>=2.11.9
Requires-Dist: fastmcp>=2.12.4 ; extra == 'mcp'
Requires-Python: >=3.13
Project-URL: Issues, https://github.com/briandconnelly/orbnet/issues
Project-URL: Repository, https://github.com/briandconnelly/orbnet
Provides-Extra: mcp
